Evaluation.py
Minimization.py
SequenceModel.py
SequiturTool.py
_sequitur_.cpython-312-darwin.so
g2p.py
misc.py
sequitur.py
sequitur_.py
symbols.py
tool.py
sequitur_g2p-1.0.1668.30.data/scripts/g2p.py
sequitur_g2p-1.0.1668.30.dist-info/LICENSE
sequitur_g2p-1.0.1668.30.dist-info/METADATA
sequitur_g2p-1.0.1668.30.dist-info/WHEEL
sequitur_g2p-1.0.1668.30.dist-info/top_level.txt
sequitur_g2p-1.0.1668.30.dist-info/RECORD
