Metadata-Version: 2.1
Name: sequitur-g2p
Version: 1.0.1668.30
Summary: sequence and joint-sequence modelling tool for g2p
Home-page: https://github.com/sequitur-g2p/sequitur-g2p
Author: Maximilian Bisani
Author-email: unknown@example.com
Maintainer: Jan 'Yenda' Trmal
Maintainer-email: jtrmal@gmail.com
License: gpl-2.0
Project-URL: Original site, https://www-i6.informatik.rwth-aachen.de/web/Software/g2p.html
Project-URL: Bug Tracker, https://github.com/sequitur-g2p/sequitur-g2p/issues
Keywords: g2p grapheme-to-phoneme sequitur grapheme phoneme
Classifier: Development Status :: 6 - Mature
Classifier: Environment :: Console
Classifier: Intended Audience :: Science/Research
Classifier: License :: OSI Approved :: GNU General Public License v2 (GPLv2)
Classifier: Operating System :: OS Independent
Classifier: Topic :: Scientific/Engineering
Classifier: Programming Language :: Python
Classifier: Programming Language :: Python :: 3
Classifier: Programming Language :: Python :: 3.9
Classifier: Programming Language :: Python :: 3.10
Classifier: Programming Language :: Python :: 3.11
Classifier: Programming Language :: Python :: 3.12
Requires-Python: >=3.9.0
License-File: LICENSE
Requires-Dist: numpy >=2.0.0
Requires-Dist: six >=1.11.0
